ubiconfig/__init__.py
ubiconfig/_impl/__init__.py
ubiconfig/_impl/loaders/__init__.py
ubiconfig/_impl/loaders/base.py
ubiconfig/_impl/loaders/gitlab.py
ubiconfig/_impl/loaders/local.py
ubiconfig/config_types/__init__.py
ubiconfig/config_types/content_sets.py
ubiconfig/config_types/flags.py
ubiconfig/config_types/modules.py
ubiconfig/config_types/packages.py
ubiconfig/ubi.py
ubiconfig/utils/__init__.py
ubiconfig/utils/api/__init__.py
ubiconfig/utils/api/gitlab.py
ubiconfig/utils/config_schema.json
ubiconfig/utils/config_validation.py
ubi_config-3.2.1.dist-info/LICENSE
ubi_config-3.2.1.dist-info/METADATA
ubi_config-3.2.1.dist-info/WHEEL
ubi_config-3.2.1.dist-info/RECORD
