Metadata-Version: 2.3
Name: ubi-config
Version: 3.2.1
Summary: A Python Library for accessing Universal Base Image configuration
License: GPL-3.0-or-later
Requires-Python: >=3.9,<4.0
Classifier: Development Status :: 4 - Beta
Classifier: Intended Audience :: Developers
Classifier: License :: OSI Approved :: GNU General Public License v3 or later (GPLv3+)
Classifier: Programming Language :: Python :: 3
Classifier: Programming Language :: Python :: 3.9
Classifier: Programming Language :: Python :: 3.10
Classifier: Programming Language :: Python :: 3.11
Classifier: Programming Language :: Python :: 3.12
Classifier: Programming Language :: Python :: 3.13
Classifier: Topic :: Software Development :: Libraries :: Python Modules
Requires-Dist: PyYAML
Requires-Dist: jsonschema
Requires-Dist: requests
Project-URL: Documentation, https://release-engineering.github.io/ubi-config
Project-URL: Repository, https://github.com/release-engineering/ubi-config
